tau_eval/__init__.py
tau_eval/experiment.py
tau_eval/logger.py
tau_eval/utils.py
tau_eval/visualization.py
tau_eval/metrics/bertscore.py
tau_eval/metrics/cola.py
tau_eval/metrics/luar.py
tau_eval/metrics/meteor.py
tau_eval/metrics/nli.py
tau_eval/metrics/perplexity.py
tau_eval/metrics/rouge.py
tau_eval/metrics/sbert.py
tau_eval/models/__init__.py
tau_eval/models/anonymizer.py
tau_eval/models/authorship.py
tau_eval/models/dummy.py
tau_eval/models/llm_api.py
tau_eval/models/presidio.py
tau_eval/models/styleremix.py
tau_eval/tasks/__init__.py
tau_eval/tasks/customtask.py
tau_eval/tasks/deidentification.py
tau_eval/tasks/imdb_authorship_classification.py
tau_eval-0.2.0.dist-info/licenses/LICENSE
tau_eval-0.2.0.dist-info/METADATA
tau_eval-0.2.0.dist-info/WHEEL
tau_eval-0.2.0.dist-info/top_level.txt
tau_eval-0.2.0.dist-info/RECORD
