Metadata-Version: 2.4
Name: tau-eval
Version: 0.2.0
Summary: Text Anonymization Evaluation Library
Author-email: Gabriel Loiseau <gabriel.loiseau@hornetsecurity.com>
Maintainer-email: Gabriel Loiseau <gabriel.loiseau@hornetsecurity.com>
License: GPL-3.0
Keywords: Text anonymization,evaluation,NLP
Classifier: Intended Audience :: Science/Research
Classifier: Programming Language :: Python :: 3.10
Classifier: Programming Language :: Python :: 3.11
Classifier: Programming Language :: Python :: 3.12
Classifier: Topic :: Scientific/Engineering :: Artificial Intelligence
Requires-Python: >=3.9
License-File: LICENSE
Requires-Dist: transformers<5.0.0,>=4.48.0
Requires-Dist: sentence-transformers>=3.3.1
Requires-Dist: torch>=2.5.0
Requires-Dist: evaluate>=0.4.1
Requires-Dist: datasets>=2.14.4
Requires-Dist: huggingface-hub>=0.20.0
Requires-Dist: tasknet>=1.57.0
Requires-Dist: tasksource>=0.0.47
Requires-Dist: ipywidgets>=8.1.5
Requires-Dist: ipykernel>=6.29.5
Requires-Dist: rich>=14.0.0
Requires-Dist: accelerate>=1.6.0
Requires-Dist: bert-score>=0.3.13
Requires-Dist: nltk>=3.9.1
Requires-Dist: rouge-score>=0.1.2
Requires-Dist: faker>=37.1.0
Requires-Dist: presidio-analyzer>=2.2.358
Requires-Dist: presidio-anonymizer>=2.2.358
Requires-Dist: pip>=25.0.1
Requires-Dist: pytest>=8.3.5
Requires-Dist: numpy>=2.0.2
Requires-Dist: matplotlib>=3.9.4
Provides-Extra: tests
Requires-Dist: pytest; extra == "tests"
Requires-Dist: accelerate>=0.20.3; extra == "tests"
Provides-Extra: quality
Requires-Dist: ruff; extra == "quality"
Requires-Dist: pyyaml>=5.3.1; extra == "quality"
Dynamic: license-file
